{
    "fluentMethods": true,
    "relationships": [
        {
            "relationshipType": "one-to-many",
            "relationshipName": "orders",
            "otherEntityName": "orders",
            "otherEntityRelationshipName": "customer"
        }
    ],
    "fields": [
        {
            "fieldName": "firstName",
            "fieldType": "String",
            "fieldValidateRules": [
                "required"
            ]
        },
        {
            "fieldName": "lastName",
            "fieldType": "String",
            "fieldValidateRules": [
                "required"
            ]
        },
        {
            "fieldName": "email",
            "fieldType": "String",
            "fieldValidateRules": [
                "required"
            ]
        },
        {
            "fieldName": "phoneNumber",
            "fieldType": "String",
            "fieldValidateRules": [
                "required"
            ]
        },
        {
            "fieldName": "activated",
            "fieldType": "Boolean",
            "fieldValidateRules": [
                "required"
            ]
        }
    ],
    "changelogDate": "20161222100948",
    "entityTableName": "customer",
    "dto": "mapstruct",
    "pagination": "pagination",
    "service": "serviceClass"
}